acl_mngt.py
acl_mngt-0.1.7.dist-info/WHEEL
acl_mngt-0.1.7.dist-info/METADATA
acl_mngt-0.1.7.dist-info/RECORD
