Metadata-Version: 2.1
Name: acl-mngt
Version: 0.1.7
Summary: Parse acl config as string, generate vendor specific config.
Home-page: https://github.com/Nextpertise/acl_mngt/
Author: Teun Ouwehand
Author-email: teun@nextpertise.nl
Requires-Python: >=3.8,<4.0
Classifier: Programming Language :: Python :: 3
Classifier: Programming Language :: Python :: 3.8
Classifier: Programming Language :: Python :: 3.9
Project-URL: Repository, https://github.com/Nextpertise/acl_mngt/
